godata/__init__.py
godata/cli/cli.py
godata/cli/ie.py
godata/cli/project.py
godata/cli/server.py
godata/cli/utils.py
godata/client/__init__.py
godata/client/client.py
godata/client/parser.py
godata/client/unixsocket.py
godata/config.py
godata/errors.py
godata/files/__init__.py
godata/files/utils.py
godata/ie.py
godata/io/__init__.py
godata/io/fitsio.py
godata/io/jsonio.py
godata/io/numpyio.py
godata/io/pandasio.py
godata/io/polarsio.py
godata/project.py
godata/server/__init__.py
godata/server/cmd.py
godata/server/config.py
godata/server/install.py
godata/utils.py
godata-0.10.1.dist-info/LICENSE
godata-0.10.1.dist-info/METADATA
godata-0.10.1.dist-info/WHEEL
godata-0.10.1.dist-info/entry_points.txt
godata-0.10.1.dist-info/RECORD
